{
  "updated_at": "2026-02-08 21:43:14",
  "entries": [
    {
      "filename": "2026-02-08_2143.json",
      "date": "2026-02-08",
      "time": "21:43",
      "path": "data/history/2026-02-08_2143.json"
    },
    {
      "filename": "2026-02-06_2146.json",
      "date": "2026-02-06",
      "time": "21:46",
      "path": "data/history/2026-02-06_2146.json"
    },
    {
      "filename": "2026-02-06_1218.json",
      "date": "2026-02-06",
      "time": "12:18",
      "path": "data/history/2026-02-06_1218.json"
    },
    {
      "filename": "2026-02-06_0932.json",
      "date": "2026-02-06",
      "time": "09:32",
      "path": "data/history/2026-02-06_0932.json"
    },
    {
      "filename": "2026-02-05_2151.json",
      "date": "2026-02-05",
      "time": "21:51",
      "path": "data/history/2026-02-05_2151.json"
    },
    {
      "filename": "2026-02-05_1219.json",
      "date": "2026-02-05",
      "time": "12:19",
      "path": "data/history/2026-02-05_1219.json"
    },
    {
      "filename": "2026-02-05_0932.json",
      "date": "2026-02-05",
      "time": "09:32",
      "path": "data/history/2026-02-05_0932.json"
    },
    {
      "filename": "2026-02-04_2315.json",
      "date": "2026-02-04",
      "time": "23:15",
      "path": "data/history/2026-02-04_2315.json"
    }
  ]
}